cemaf/__init__.py
cemaf/agents/__init__.py
cemaf/agents/base.py
cemaf/agents/factories.py
cemaf/agents/protocols.py
cemaf/blueprint/__init__.py
cemaf/blueprint/builder.py
cemaf/blueprint/factories.py
cemaf/blueprint/mock.py
cemaf/blueprint/protocols.py
cemaf/blueprint/rules.py
cemaf/blueprint/schema.py
cemaf/cache/__init__.py
cemaf/cache/decorators.py
cemaf/cache/factories.py
cemaf/cache/mock.py
cemaf/cache/protocols.py
cemaf/cache/stores.py
cemaf/citation/__init__.py
cemaf/citation/factories.py
cemaf/citation/mock.py
cemaf/citation/models.py
cemaf/citation/protocols.py
cemaf/citation/rules.py
cemaf/citation/tracker.py
cemaf/config/__init__.py
cemaf/config/factories.py
cemaf/config/loader.py
cemaf/config/mock.py
cemaf/config/protocols.py
cemaf/context/__init__.py
cemaf/context/advanced_compiler.py
cemaf/context/algorithm.py
cemaf/context/budget.py
cemaf/context/compiler.py
cemaf/context/context.py
cemaf/context/factories.py
cemaf/context/merge.py
cemaf/context/patch.py
cemaf/context/paths.py
cemaf/context/protocols.py
cemaf/context/source.py
cemaf/core/__init__.py
cemaf/core/constants.py
cemaf/core/enums.py
cemaf/core/execution.py
cemaf/core/registry.py
cemaf/core/result.py
cemaf/core/storage.py
cemaf/core/types.py
cemaf/core/utils.py
cemaf/evals/__init__.py
cemaf/evals/composite.py
cemaf/evals/evaluators.py
cemaf/evals/factories.py
cemaf/evals/llm_judge.py
cemaf/evals/protocols.py
cemaf/evals/semantic.py
cemaf/events/__init__.py
cemaf/events/bus.py
cemaf/events/factories.py
cemaf/events/mock.py
cemaf/events/notifiers.py
cemaf/events/protocols.py
cemaf/generation/__init__.py
cemaf/generation/factories.py
cemaf/generation/mock.py
cemaf/generation/protocols.py
cemaf/ingestion/__init__.py
cemaf/ingestion/adapters.py
cemaf/ingestion/factories.py
cemaf/ingestion/protocols.py
cemaf/llm/__init__.py
cemaf/llm/factories.py
cemaf/llm/mock.py
cemaf/llm/protocols.py
cemaf/llm/response_utils.py
cemaf/llm/tiktoken_estimator.py
cemaf/mcp/__init__.py
cemaf/mcp/adapter.py
cemaf-0.1.0.dist-info/METADATA
cemaf-0.1.0.dist-info/WHEEL
cemaf-0.1.0.dist-info/licenses/LICENSE
cemaf-0.1.0.dist-info/RECORD
