Metadata-Version: 2.4
Name: cemaf
Version: 0.1.0
Summary: Context Engineering Multi-Agent Framework - A pluggable, modular framework for building AI agent systems
Project-URL: Homepage, https://github.com/drchinca/cemaf
Project-URL: Documentation, https://github.com/drchinca/cemaf/blob/main/docs/README.md
Project-URL: Repository, https://github.com/drchinca/cemaf
Project-URL: Bug Tracker, https://github.com/drchinca/cemaf/issues
Project-URL: Discussions, https://github.com/drchinca/cemaf/discussions
Project-URL: Discord Community, https://discord.gg/C8ZXAbD8
Project-URL: Changelog, https://github.com/drchinca/cemaf/blob/main/CHANGELOG.md
Project-URL: Source Code, https://github.com/drchinca/cemaf
Author-email: Hikuri Bado Chinca <chincadr@gmail.com>
License: MIT
License-File: LICENSE
Keywords: agents,ai,autogen,context-engineering,context-management,crewai,dag,framework-agnostic,langchain,langgraph,llm,multi-agent,orchestration,provenance,replay,token-budgeting
Classifier: Development Status :: 3 - Alpha
Classifier: Framework :: AsyncIO
Classifier: Intended Audience :: Developers
Classifier: Intended Audience :: Science/Research
Classifier: License :: OSI Approved :: MIT License
Classifier: Operating System :: OS Independent
Classifier: Programming Language :: Python :: 3
Classifier: Programming Language :: Python :: 3 :: Only
Classifier: Programming Language :: Python :: 3.14
Classifier: Topic :: Scientific/Engineering :: Artificial Intelligence
Classifier: Topic :: Software Development :: Libraries :: Application Frameworks
Classifier: Topic :: Software Development :: Libraries :: Python Modules
Classifier: Typing :: Typed
Requires-Python: >=3.14
Requires-Dist: pydantic>=2.0
Requires-Dist: typing-extensions>=4.9
Provides-Extra: all
Requires-Dist: anthropic>=0.20; extra == 'all'
Requires-Dist: openai>=1.0; extra == 'all'
Requires-Dist: tiktoken>=0.5; extra == 'all'
Provides-Extra: anthropic
Requires-Dist: anthropic>=0.20; extra == 'anthropic'
Provides-Extra: dev
Requires-Dist: bandit[toml]>=1.7; extra == 'dev'
Requires-Dist: mypy>=1.8; extra == 'dev'
Requires-Dist: pre-commit>=4.0; extra == 'dev'
Requires-Dist: pytest-asyncio>=0.23; extra == 'dev'
Requires-Dist: pytest-cov>=4.0; extra == 'dev'
Requires-Dist: pytest>=8.0; extra == 'dev'
Requires-Dist: ruff>=0.3; extra == 'dev'
Provides-Extra: openai
Requires-Dist: openai>=1.0; extra == 'openai'
Requires-Dist: tiktoken>=0.5; extra == 'openai'
Provides-Extra: pinecone
Requires-Dist: pinecone-client>=3.0; extra == 'pinecone'
Provides-Extra: profiling
Requires-Dist: line-profiler>=4.2.0; extra == 'profiling'
Requires-Dist: memory-profiler>=0.61.0; extra == 'profiling'
Requires-Dist: pytest-benchmark>=5.1.0; extra == 'profiling'
Provides-Extra: tiktoken
Requires-Dist: tiktoken>=0.5; extra == 'tiktoken'
